finecode_extension_api/__init__.py
finecode_extension_api/code_action.py
finecode_extension_api/common_types.py
finecode_extension_api/partialresultscheduler.py
finecode_extension_api/py.typed
finecode_extension_api/textstyler.py
finecode_extension_api/actions/__init__.py
finecode_extension_api/actions/build.py
finecode_extension_api/actions/check_formatting.py
finecode_extension_api/actions/dump_config.py
finecode_extension_api/actions/format.py
finecode_extension_api/actions/install_deps_in_env.py
finecode_extension_api/actions/lint.py
finecode_extension_api/actions/prepare_envs.py
finecode_extension_api/actions/prepare_runners.py
finecode_extension_api/actions/ide/__init__.py
finecode_extension_api/actions/ide/text_document_code_action.py
finecode_extension_api/actions/ide/text_document_inlay_hint.py
finecode_extension_api/interfaces/__init__.py
finecode_extension_api/interfaces/iactionrunner.py
finecode_extension_api/interfaces/icache.py
finecode_extension_api/interfaces/icommandrunner.py
finecode_extension_api/interfaces/ifilemanager.py
finecode_extension_api/interfaces/ilogger.py
finecode_extension_api/interfaces/iprocessexecutor.py
finecode_extension_api/interfaces/iprojectinfoprovider.py
finecode_extension_api-0.3.0.dist-info/METADATA
finecode_extension_api-0.3.0.dist-info/WHEEL
finecode_extension_api-0.3.0.dist-info/top_level.txt
finecode_extension_api-0.3.0.dist-info/RECORD
