Metadata-Version: 2.4
Name: finecode-extension-api
Version: 0.3.0
Author-email: Vladyslav Hnatiuk <aders1234@gmail.com>
Requires-Python: <3.14,>=3.11
Requires-Dist: typing-extensions<5.0.0,>=4.12.2
